{
  "districts": {
    "alipurduar": {
      "code": "020",
      "ps": {
        "falakata": "0032",
        "birpara": "0036",
        "madarihat": "0037",
        "jaigaon": "0033",
        "kalchini": "0034",
        "alipurduar": "0030",
        "samuktola": "0031",
        "kumargram": "0035",
        "alipurduar ps": "0446"
      }
    },
    "bankura": {
      "code": "001",
      "ps": {
        "bankura": "0140",
        "beliatore": "0141",
        "chhatna": "0146",
        "saltora": "0162",
        "mejia": "0155",
        "gangajalghati": "0148",
        "barjora": "0144",
        "onda": "0156",
        "taldangra": "0166",
        "simlapal": "0164",
        "khatra": "0153",
        "hirbandh": "0149",
        "indpur": "0151",
        "barikul": "0158",
        "raipur": "0159",
        "sarenga": "0163",
        "ranibandh": "0161",
        "bishnupur": "0145",
        "joypur": "0152",
        "kotulpur": "0154",
        "sonamukhi": "0165",
        "patrasayer": "0157",
        "indas": "0150",
        "bankura ps": "0447",
        "bishnupur ps": "0449",
        "sonamukhi ps": "0448"
      }
    },
    "birbhum": {
      "code": "003",
      "ps": {
        "nalhati": "0136",
        "murarai": "0138",
        "murari-1": "0570",
        "paikar": "0139",
        "mallarpur": "0131",
        "mayureswar": "0132",
        "rampurhat": "0133",
        "margram": "0134",
        "tarapith": "0135",
        "md bazar": "0119",
        "sainthia": "0118",
        "bolpur": "0126",
        "santiniketan": "0127",
        "labpur": "0129",
        "nanoor": "0130",
        "dubrajpur": "0120",
        "illamabazar": "0128",
        "chandrapur": "0124",
        "rajnagar": "0125",
        "sadaipur": "0115",
        "suri": "0116",
        "panrui": "0117",
        "suri ps": "0581",
        "lokpur": "0121",
        "kankartala": "0122",
        "khoyrasole": "0123",
        "bolpur ps": "0451",
        "dubrajpur ps": "0450",
        "nalhati ps": "0452",
        "rampurhat ps": "0453",
        "sainthia ps": "0454"
      }
    },
    "coochbihar": {
      "code": "008",
      "ps": {
        "kotwali": "0038",
        "pundibari": "0039",
        "tufanganj": "0040",
        "boxirhat": "0041",
        "dinhata": "0042",
        "sahebganj": "0043",
        "sitai": "0044",
        "haldibari": "0048",
        "kuchlibari": "0049",
        "mekhliganj": "0050",
        "mathabhanga": "0045",
        "ghoksadanga": "0046",
        "sitalkuchi": "0047",
        "cooch behar kotwali ps": "0458",
        "dinhata ps": "0459",
        "haldibari ps": "0456",
        "mathabhanga ps": "0460",
        "mekliganj ps": "0457",
        "tufanganj ps": "0461"
      }
    },
    "dakshin 24 pargana": {
      "code": "016",
      "ps": {
        "baruipur": "0421",
        "klc": "0422",
        "bhangore": "0423",
        "kashipur": "0425",
        "bishnupur": "0393",
        "nodakhali": "0395",
        "pujali": "0396",
        "budge budge": "0397",
        "jharkhali coastal": "0401",
        "basanti": "0402",
        "jibantala": "0403",
        "canning": "0404",
        "joynagar": "0426",
        "kultali": "0427",
        "bakultala": "0428",
        "maipith coastal": "0430",
        "rabindranagar": "0399",
        "maheshtala": "0400",
        "narendrapur": "0431",
        "sonarpur": "0432",
        "sundarban costal": "0406",
        "gosaba": "0407",
        "parulia costal": "0433",
        "diamond harbour": "0434",
        "ramnagar": "0435",
        "dholahat": "0443",
        "mathurapur": "0444",
        "raidighi": "0445",
        "usthi": "0440",
        "magrahat": "0441",
        "mandirbazar": "0442",
        "fresergunj costal": "0411",
        "kakdwip": "0412",
        "namkhana": "0413",
        "kulpi": "0439",
        "harwood point coastal": "0408",
        "gobardhanpur costal": "0414",
        "patharpratima": "0415",
        "falta": "0437",
        "sagar costal": "0419",
        "sagar": "0420",
        "baruipur ps": "0559",
        "budge budge ps": "0560",
        "diamond harbour ps": "0563",
        "jaynagar ps": "0561",
        "maheshtala ps": "0562",
        "pujali ps": "0564",
        "sonarpur ps": "0565"
      }
    },
    "dakshin dinajpur": {
      "code": "017",
      "ps": {
        "balurghat": "0066",
        "hili": "0070",
        "kumarganj": "0065",
        "tapan": "0067",
        "gangarampur": "0064",
        "banshihari": "0068",
        "harirampur": "0063",
        "kushmandi": "0069",
        "balurghat ps": "0463",
        "banshihari ps": "0462",
        "gangarampur ps": "0464"
      }
    },
    "darjeeling": {
      "code": "004",
      "ps": {
        "pradhan nagar": "0010",
        "bagdogra": "0011",
        "matigara": "0012",
        "naxalbari": "0009",
        "phansidewa": "0015",
        "khoribari": "0013",
        "kurseong": "0007",
        "mirik": "0008",
        "rangli- rangliot": "0001",
        "jorebunglow": "0002",
        "sukhiapokhri": "0003",
        "lodhama": "0004",
        "pulbazar": "0005",
        "sadar": "0006",
        "siliguri mc ps": "0468",
        "darjeeling ps": "0465",
        "kurseong ps": "0466",
        "mirik ps": "0467"
      }
    },
    "hooghly": {
      "code": "006",
      "ps": {
        "mogra": "0318",
        "chinsurah": "0319",
        "dadpur": "0329",
        "polba": "0330",
        "gurap": "0320",
        "dhaniakhali": "0321",
        "pandua": "0328",
        "balagarh": "0315",
        "singur": "0335",
        "haripal": "0324",
        "goghat": "0336",
        "serampore": "0333",
        "uttarpara": "0334",
        "chanditala": "0316",
        "arambagh": "0314",
        "khanakul": "0326",
        "pursurah": "0332",
        "chandernagore ps": "0473",
        "arambagh ps": "0469",
        "serampore ps": "0470",
        "morgra ps": "0479",
        "bhadreswar ps": "0471",
        "dankuni ps": "0474",
        "hooghly chinsurah ps": "0480",
        "uttarpara kottung ps": "0475",
        "rishra ps & srerampore ps": "0476",
        "tarakeswar ps": "0478"
      }
    },
    "howrah": {
      "code": "005",
      "ps": {
        "domjur": "0342",
        "jagatballavpur": "0343",
        "liluah": "0341",
        "sankrail": "0345",
        "panchla": "0344",
        "amta": "0337",
        "joypur": "0338",
        "bagnan": "0339",
        "udayanarayan": "0348",
        "uluberia": "0349",
        "shyampur": "0346",
        "howrah commissionerate": "0482",
        "uluberia ps": "0483"
      }
    },
    "jalpaiguri": {
      "code": "007",
      "ps": {
        "bhaktinagar": "0028",
        "rajganj": "0029",
        "kotwali": "0027",
        "maynaguri": "0023",
        "dhupguri": "0026",
        "mal": "0024",
        "matiali": "0020",
        "banarhat": "0021",
        "nagrakata": "0022",
        "dhupguri ps": "0484",
        "mal bazar ps": "0486",
        "jalpaiguri kotwali ps": "0485",
        "kranti op": "0577"
      }
    },
    "jhargram": {
      "code": "022",
      "ps": {
        "nayagram": "0243",
        "gopiballavpur": "0245",
        "beliaberah": "0246",
        "sankrail": "0252",
        "jhargram": "0244",
        "jamboni": "0251",
        "lalgarh": "0247",
        "binpur": "0248",
        "belpahari": "0250",
        "jhargram ps": "0487"
      }
    },
    "kalimpong": {
      "code": "021",
      "ps": {
        "kalimpong": "0016",
        "jaldhaka": "0018",
        "gorubathan": "0019",
        "kalimpong ps": "0488"
      }
    },
    "kolkata": {
      "code": "019",
      "ps": {
        "north port": "0571",
        "bansdroni": "0572",
        "behala": "0573",
        "raja bagan": "0574",
        "pragati maidan": "0575",
        "manicktolla": "0576",
        "south port": "0584",
        "lake police station": "0586"
      }
    },
    "malda": {
      "code": "009",
      "ps": {
        "harishchandrapur": "0082",
        "chanchal": "0080",
        "ratua": "0084",
        "manikchak": "0076",
        "maldaha": "0079",
        "gazole": "0077",
        "bamongola": "0078",
        "habibpur": "0072",
        "englishbazar": "0071",
        "kaliachak": "0073",
        "mothabari": "0074",
        "baishnab nagar": "0075",
        "englishbazar ps": "0489",
        "old malda ps": "0490"
      }
    },
    "murshidabad": {
      "code": "012",
      "ps": {
        "beldanga": "0086",
        "saktipur": "0087",
        "rejinagar": "0088",
        "berhampore doulatabad": "0089",
        "bhagwangola": "0090",
        "ranitala": "0091",
        "bharatpur": "0092",
        "salar": "0093",
        "burwan": "0094",
        "domkal": "0095",
        "farakka": "0096",
        "hariharpara": "0097",
        "sagarpara": "0098",
        "jalangi": "0099",
        "kandi": "0100",
        "khargram": "0101",
        "lalgola": "0102",
        "jiaganj": "0103",
        "murshidabad": "0104",
        "nabagram": "0105",
        "nowda": "0106",
        "raghunathganj": "0107",
        "islampur": "0109",
        "raninagar": "0110",
        "sagardighi": "0111",
        "samserganj": "0112",
        "suti": "0113",
        "beldanga ps": "0491",
        "berhampore ps": "0494",
        "samsergunj ps": "0492",
        "domkal ps": "0493",
        "raghunathgunj ps": "0495",
        "jiaganj ps": "0497",
        "kandi ps": "0496",
        "murshidabad ps": "0498"
      }
    },
    "nadia": {
      "code": "013",
      "ps": {
        "chakdaha": "0312",
        "chapra": "0309",
        "hanskhali": "0295",
        "haringhata": "0313",
        "kaliganj": "0307",
        "murutia": "0290",
        "hogalberia": "0291",
        "natidanga": "0292",
        "krishnaganj": "0302",
        "bhimpur": "0303",
        "krishnagar women": "0304",
        "kotwali": "0305",
        "dhubulia": "0306",
        "nabadwip": "0301",
        "bethuadahari": "0308",
        "ranaghat women": "0297",
        "taherpur": "0298",
        "ranaghat": "0299",
        "gangnapur": "0300",
        "santipur": "0296",
        "palashipara": "0293",
        "tehatta": "0294",
        "kalyani women": "0310",
        "kalyani": "0311",
        "taherpur ps": "0499",
        "chakdah ps": "0502",
        "ranaghat ps": "0500",
        "kalyani ps": "0501",
        "haringhata ps": "0504",
        "nabadwip ps": "0506",
        "santipur ps": "0508"
      }
    },
    "paschim bardhaman": {
      "code": "023",
      "ps": {
        "andal": "0253",
        "faridpur": "0255",
        "kanksa": "0257",
        "pandaveshwar": "0258",
        "barabani": "0254",
        "jamuria": "0256",
        "raniganj": "0259",
        "chittaranjan": "0260",
        "salanpur": "0261",
        "chittaranjan ct": "0578",
        "asansol south ps": "0536",
        "assansol north": "0538",
        "kulti": "0539",
        "hirapur": "0541",
        "new township ps & coke oven ps": "0537",
        "durgapur": "0542",
        "new township": "0543",
        "coke oven": "0544"
      }
    },
    "purba bardhhaman": {
      "code": "002",
      "ps": {
        "burdwan sadar": "0262",
        "dewandighi": "0263",
        "memari": "0278",
        "jamalpur": "0277",
        "raina": "0275",
        "madhabdihi": "0276",
        "khandaghosh": "0274",
        "bhatar": "0267",
        "ausgram": "0268",
        "budbud": "0269",
        "galsi": "0273",
        "saktigarh": "0266",
        "katwa": "0285",
        "ketugram": "0287",
        "mongalkote": "0289",
        "kalna": "0280",
        "nadanghat": "0282",
        "purbasthali": "0283",
        "moteswar": "0284",
        "burdwan ps": "0548",
        "katwa ps": "0545",
        "aushgram ps": "0549",
        "kalna ps": "0546",
        "memari ps": "0550"
      }
    },
    "purba medinipur": {
      "code": "011",
      "ps": {
        "panskura": "0215",
        "kolaghat": "0216",
        "tamluk": "0218",
        "moyna": "0220",
        "mahishadal": "0223",
        "nandakumar": "0221",
        "sutahata": "0224",
        "nandigram": "0226",
        "chandipur": "0222",
        "bhagwanpur": "0242",
        "bhupatinagar": "0237",
        "khejuri": "0235",
        "contai": "0229",
        "marishda": "0230",
        "patashpur": "0240",
        "egra": "0238",
        "digha mohana": "0231",
        "digha": "0232",
        "ramnagar": "0233",
        "durgachak": "0225",
        "contai ps": "0551",
        "egra ps": "0552",
        "haldia ps": "0553",
        "panskura ps": "0554",
        "tamralipta ps": "0555",
        "bhawanipur": "0585"
      }
    },
    "purulia": {
      "code": "014",
      "ps": {
        "tamna": "0182",
        "purulia (muffasil)": "0183",
        "hura": "0172",
        "puncha": "0181",
        "manbazar": "0177",
        "boro": "0178",
        "bundwan": "0171",
        "arsha": "0167",
        "balarampur": "0169",
        "baghmundi": "0168",
        "barabazar": "0170",
        "joypur": "0173",
        "jhalda": "0174",
        "kotshila": "0175",
        "raghunathpur": "0185",
        "santaldih": "0186",
        "para": "0180",
        "kashipur": "0176",
        "neturia": "0179",
        "santuri": "0187",
        "jhalda ps": "0556",
        "purulia town ps": "0557",
        "raghunathpur ps": "0558"
      }
    },
    "uttar 24 pargana": {
      "code": "015",
      "ps": {
        "amdanga": "0368",
        "duttapukur": "0364",
        "rajarhat": "0365",
        "sashan": "0366",
        "madhyamgram": "0367",
        "deganga": "0369",
        "habra, gobardanga": "0370",
        "ashoknagar": "0371",
        "dumdum": "0372",
        "narayanpur": "0373",
        "baguihati": "0374",
        "airport": "0375",
        "new town": "0376",
        "eco park": "0377",
        "technocity": "0378",
        "jagaddal": "0356",
        "bhatpara": "0357",
        "naihati": "0358",
        "bijpur": "0359",
        "rahara": "0360",
        "titagarh": "0361",
        "khardah": "0362",
        "ghola": "0363",
        "barduria": "0381",
        "basirhat": "0387",
        "matia": "0388",
        "haroa": "0382",
        "hasnabad": "0389",
        "hemnagar coastal": "0390",
        "hingalganj": "0392",
        "minakhan": "0383",
        "nazat": "0385",
        "sandeshkhali": "0386",
        "swarupnaga": "0380",
        "petrapol": "0351",
        "gopalnagar": "0352",
        "bongaon": "0353",
        "bagdah": "0354",
        "gaighata": "0355",
        "ashokenagar kalyangarh ps": "0510",
        "baduria ps": "0511",
        "baranagar ps": "0512",
        "barasat ps": "0513",
        "barrackpore ps": "0514",
        "basirhat ps": "0515",
        "bhatpara ps": "0516",
        "bidhannagar south ps": "0517",
        "bongaon ps": "0518",
        "dum dum ps": "0519",
        "nowapara ps & jagaddal ps": "0520",
        "gobardanga ps": "0521",
        "habra ps": "0522",
        "halisahar": "0523",
        "kamarhati": "0524",
        "kanchrapara": "0525",
        "new barrackpore": "0529",
        "north barrackpore": "0530",
        "north dum dum": "0531",
        "panihati": "0532",
        "taki": "0534"
      }
    },
    "uttar dinajpur": {
      "code": "018",
      "ps": {
        "chopra": "0051",
        "islampur": "0052",
        "goalpokhar": "0053",
        "dalkhola": "0054",
        "chakulia": "0056",
        "karandighi": "0058",
        "raiganj": "0061",
        "hemtabad": "0059",
        "kaliaganj": "0060",
        "itahar": "0062",
        "dalkhola ps": "0568",
        "islampur ps": "0566",
        "kaliaganj ps": "0567",
        "raiganj ps": "0569"
      }
    }
  }
}